README.md
setup.py
ign_lidarutils.egg-info/PKG-INFO
ign_lidarutils.egg-info/SOURCES.txt
ign_lidarutils.egg-info/dependency_links.txt
ign_lidarutils.egg-info/top_level.txt
lidarutils/__init__.py
lidarutils/bduni_utils.py
lidarutils/conda_utils.py
lidarutils/file_utils.py
lidarutils/gdal_calc.py
lidarutils/gdal_utils.py
lidarutils/geojson_utils.py
lidarutils/geometry_utils.py
lidarutils/gpao_utils.py
lidarutils/las_ign_utils.py
lidarutils/pdal_pipeline.py
lidarutils/rge_alti_extract_from_gpp.py
test/test_bduni_utils.py
test/test_conda_utils.py
test/test_las_ign_utils.py
test/test_pdal_pipelines.py
test/test_rge_alti_extract_from_gpp.py