Metadata-Version: 2.1
Name: ign-lidarutils
Version: 0.0.7
Summary: Lidar utils Python package
Author: Antoine Lavenant
Author-email: <antoine.lavenant@ign.fr>
License: UNKNOWN
Keywords: python,lidar
Platform: UNKNOWN
Classifier: Development Status :: 3 - Alpha
Classifier: Intended Audience :: Education
Classifier: Programming Language :: Python :: 2
Classifier: Programming Language :: Python :: 3
Classifier: Operating System :: MacOS :: MacOS X
Classifier: Operating System :: Microsoft :: Windows
